swab/__init__.py
swab/test_swab.py
swab/static/swab.css
swab/templates/results.html
swab-0.2.3.dist-info/LICENSE.txt
swab-0.2.3.dist-info/METADATA
swab-0.2.3.dist-info/WHEEL
swab-0.2.3.dist-info/top_level.txt
swab-0.2.3.dist-info/RECORD
