Metadata-Version: 2.1
Name: swab
Version: 0.2.3
Summary: Swab: Simple WSGI A/B testing
Home-page: https://ollycope.com/software/swab/
Author: Oliver Cope
Author-email: oliver@redgecko.org
License: BSD
Keywords: ab,a/b,a/bingo,split testing
Classifier: Development Status :: 3 - Alpha
Classifier: Environment :: Web Environment
Classifier: License :: OSI Approved :: BSD License
Classifier: Programming Language :: Python
License-File: LICENSE.txt
Requires-Dist: fresco
Requires-Dist: fresco-static
Requires-Dist: fresco-template
Requires-Dist: piglet-templates
